crudbuilder/__init__.py
crudbuilder/abstract.py
crudbuilder/exceptions.py
crudbuilder/formset.py
crudbuilder/helpers.py
crudbuilder/mixins.py
crudbuilder/registry.py
crudbuilder/signals.py
crudbuilder/tables.py
crudbuilder/urls.py
crudbuilder/views.py
crudbuilder/static/crudbuilder/css/bootstrap-theme.css
crudbuilder/static/crudbuilder/css/bootstrap-theme.css.map
crudbuilder/static/crudbuilder/css/bootstrap-theme.min.css
crudbuilder/static/crudbuilder/css/bootstrap-theme.min.css.map
crudbuilder/static/crudbuilder/css/bootstrap.css
crudbuilder/static/crudbuilder/css/bootstrap.css.map
crudbuilder/static/crudbuilder/css/bootstrap.min.css
crudbuilder/static/crudbuilder/css/bootstrap.min.css.map
crudbuilder/static/crudbuilder/fonts/glyphicons-halflings-regular.eot
crudbuilder/static/crudbuilder/fonts/glyphicons-halflings-regular.svg
crudbuilder/static/crudbuilder/fonts/glyphicons-halflings-regular.ttf
crudbuilder/static/crudbuilder/fonts/glyphicons-halflings-regular.woff
crudbuilder/static/crudbuilder/fonts/glyphicons-halflings-regular.woff2
crudbuilder/static/crudbuilder/js/bootstrap.js
crudbuilder/static/crudbuilder/js/bootstrap.min.js
crudbuilder/static/crudbuilder/js/jquery-1.11.3.js
crudbuilder/static/crudbuilder/js/jquery.formset.js
crudbuilder/static/crudbuilder/js/npm.js
crudbuilder/templates/crudbuilder/base.html
crudbuilder/templates/crudbuilder/cruds.html
crudbuilder/templates/crudbuilder/inline/create.html
crudbuilder/templates/crudbuilder/inline/delete.html
crudbuilder/templates/crudbuilder/inline/detail.html
crudbuilder/templates/crudbuilder/inline/list.html
crudbuilder/templates/crudbuilder/inline/update.html
crudbuilder/templates/crudbuilder/instance/create.html
crudbuilder/templates/crudbuilder/instance/delete.html
crudbuilder/templates/crudbuilder/instance/detail.html
crudbuilder/templates/crudbuilder/instance/list.html
crudbuilder/templates/crudbuilder/instance/update.html
crudbuilder/templates/crudbuilder/widgets/form.html
django_crudbuilder-0.2.8.dist-info/LICENSE.txt
django_crudbuilder-0.2.8.dist-info/METADATA
django_crudbuilder-0.2.8.dist-info/WHEEL
django_crudbuilder-0.2.8.dist-info/top_level.txt
django_crudbuilder-0.2.8.dist-info/RECORD
