Metadata-Version: 2.1
Name: django-crudbuilder
Version: 0.2.8
Summary: A simple Django CRUD builder
Home-page: https://github.com/asifpy/django-crudbuilder
Author: Asif Jamadar
Author-email: saluasif@gmail.com
License: BSD License
Classifier: Environment :: Web Environment
Classifier: Framework :: Django
Classifier: Intended Audience :: Developers
Classifier: License :: OSI Approved :: BSD License
Classifier: Operating System :: OS Independent
Classifier: Programming Language :: Python
Classifier: Programming Language :: Python :: 2.7
Classifier: Programming Language :: Python :: 3.3
Classifier: Programming Language :: Python :: 3.4
Classifier: Programming Language :: Python :: 3.5
Classifier: Topic :: Internet :: WWW/HTTP
Classifier: Topic :: Internet :: WWW/HTTP :: Dynamic Content
License-File: LICENSE.txt
Requires-Dist: django-tables2
Requires-Dist: six (>=1.10.0)
